pulseaudio_device_control/__init__.py
pulseaudio_device_control/config.py
pulseaudio_device_control/pulseaudio_device_control.py
pulseaudio_device_control-0.4.dist-info/licenses/LICENSE
pulseaudio_device_control-0.4.dist-info/METADATA
pulseaudio_device_control-0.4.dist-info/WHEEL
pulseaudio_device_control-0.4.dist-info/entry_points.txt
pulseaudio_device_control-0.4.dist-info/top_level.txt
pulseaudio_device_control-0.4.dist-info/RECORD
