Metadata-Version: 2.4
Name: pulseaudio_device_control
Version: 0.4
Summary: A simple script to control PulseAudio devices
Author-email: Brenton Leighton <12228142+brenton-leighton@users.noreply.github.com>
Maintainer-email: Brenton Leighton <12228142+brenton-leighton@users.noreply.github.com>
License: MIT License
Project-URL: Homepage, https://github.com/brenton-leighton/pulseaudio_device_control
Keywords: pulseaudio
Requires-Python: >=3.8
License-File: LICENSE
Requires-Dist: pulsectl
Dynamic: license-file
